pysvelte/ExtJsonEncoder.py
pysvelte/SvelteComponent.py
pysvelte/__init__.py
pysvelte/config.py
pysvelte/html.py
pysvelte/javascript.py
pysvelte/publish.py
pysvelte/python_fns.py
pysvelte/vis_paths.py
noa_pysvelte-1.0.0.dist-info/LICENSE
noa_pysvelte-1.0.0.dist-info/METADATA
noa_pysvelte-1.0.0.dist-info/WHEEL
noa_pysvelte-1.0.0.dist-info/top_level.txt
noa_pysvelte-1.0.0.dist-info/RECORD
