Metadata-Version: 2.1
Name: noa-pysvelte
Version: 1.0.0
Summary: A library for visualising and interpreting model activations within a Jupyter Notebook. Fork of https://github.com/anthropics/PySvelte
Home-page: https://github.com/noanabeshima/PySvelte
Author: Noa Nabeshima
Author-email: noanabeshima@gmail.com
License: LICENSE
Classifier: Programming Language :: Python :: 3
Classifier: License :: OSI Approved :: MIT License
Classifier: Operating System :: OS Independent
Requires-Python: >=3.6
License-File: LICENSE
Requires-Dist: einops
Requires-Dist: numpy
Requires-Dist: torch
Requires-Dist: datasets
Requires-Dist: transformers
Requires-Dist: tqdm
Requires-Dist: pandas
Requires-Dist: typeguard~=2.0
